XD_Docker-0.2.0.dist-info/DESCRIPTION.rst
XD_Docker-0.2.0.dist-info/METADATA
XD_Docker-0.2.0.dist-info/RECORD
XD_Docker-0.2.0.dist-info/WHEEL
XD_Docker-0.2.0.dist-info/metadata.json
XD_Docker-0.2.0.dist-info/top_level.txt
xd/__init__.py
xd/docker/__init__.py
xd/docker/client.py
xd/docker/container.py
xd/docker/datetime.py
xd/docker/image.py
xd/docker/parameters.py
