Metadata-Version: 2.0
Name: XD-Docker
Version: 0.2.0
Summary: Python library for accessing Docker Remote API
Home-page: https://github.com/XD-embedded/xd-docker
Author: Esben Haabendal
Author-email: esben@haabendal.dk
License: MIT
Keywords: docker
Platform: UNKNOWN
Classifier: Development Status :: 3 - Alpha
Classifier: Intended Audience :: Developers
Classifier: Topic :: Software Development :: Libraries :: Python Modules
Classifier: License :: OSI Approved :: MIT License
Classifier: Programming Language :: Python
Classifier: Programming Language :: Python :: 3 :: Only
Classifier: Programming Language :: Python :: 3.4
Classifier: Programming Language :: Python :: 3.5
Requires-Dist: requests
Requires-Dist: requests-unixsocket
Requires-Dist: typing
